foresight/KernelProxyBlocking.py
foresight/__init__.py
foresight/alignment_strategies.py
foresight/board.py
foresight/celery_tasks.py
foresight/jupyterkernelproxy.py
foresight/proxy.py
foresight/room.py
foresight/smartbitcollection.py
foresight/smartbitfactory.py
foresight/smartbits_utils.py
foresight/task_scheduler.py
foresight/Sage3Sugar/__init__.py
foresight/Sage3Sugar/pysage3.py
foresight/ai/__init__.py
foresight/ai/ai_client.py
foresight/ai/tests/__init__.py
foresight/ai/tests/test_ai_client.py
foresight/config/__init__.py
foresight/json_templates/__init__.py
foresight/json_templates/templates.py
foresight/smartbits/__init__.py
foresight/smartbits/aipane.py
foresight/smartbits/chat.py
foresight/smartbits/codeeditor.py
foresight/smartbits/counter.py
foresight/smartbits/csvviewer.py
foresight/smartbits/datatable.py
foresight/smartbits/genericsmartbit.py
foresight/smartbits/gltfviewer.py
foresight/smartbits/iframe.py
foresight/smartbits/imageviewer.py
foresight/smartbits/kerneldashboard.py
foresight/smartbits/mapgl.py
foresight/smartbits/note.py
foresight/smartbits/pdfviewer.py
foresight/smartbits/sagecell.py
foresight/smartbits/seer.py
foresight/smartbits/slider.py
foresight/smartbits/smartbit.py
foresight/smartbits/stickie.py
foresight/smartbits/vegalite.py
foresight/smartbits/vegaliteviewer.py
foresight/smartbits/videoviewer.py
foresight/smartbits/webview.py
foresight/tests/__init__.py
foresight/tests/test_board.py
foresight/tests/test_envs.py
foresight/tests/test_jupyterkernelproxy.py
foresight/tests/test_linked_app.py
foresight/utils/__init__.py
foresight/utils/_logging_config.py
foresight/utils/borg.py
foresight/utils/generic_utils.py
foresight/utils/layout.py
foresight/utils/notebook.py
foresight/utils/sage_communication.py
foresight/utils/sage_websocket.py
foresight/utils/wall_utils.py
pysage3-1.0.8.dist-info/LICENSE
pysage3-1.0.8.dist-info/METADATA
pysage3-1.0.8.dist-info/WHEEL
pysage3-1.0.8.dist-info/top_level.txt
pysage3-1.0.8.dist-info/RECORD
