Metadata-Version: 2.2
Name: pysage3
Version: 1.0.8
Summary: SAGE3 API
Author-email: SAGE3 Team <sage3app@gmail.com>
Project-URL: Homepage, https://github.com/SAGE-3/next
Requires-Python: >=3.9
License-File: LICENSE
